{
    "c9a75869-c320-bc9d-395d-96ee3f0f336a": {
        "paletteKey": "FlexLayoutCol",
        "commentid": null,
        "designerReference": [
            {
                "_key": "componentLabel",
                "_value": "Column",
                "_type": "kv",
                "_attrDef": "p",
                "_useAsLabel": true
            },
            {
                "_key": "style",
                "_value": "",
                "_type": "kv",
                "_attrDef": "p"
            },
            {
                "_key": "class",
                "_value": "",
                "_type": "dav",
                "_attrDef": "p"
            },
            {
                "_key": "fxFlex",
                "_value": "",
                "_type": "kv",
                "_attrDef": "p"
            },
            {
                "_key": "fxLayoutGap",
                "_value": "",
                "_type": "kv",
                "_attrDef": "p"
            },
            {
                "_key": "wrap",
                "_value": "wrap",
                "_type": "a",
                "_attrDef": "p"
            },
            {
                "_key": "layoutAlign",
                "_value": "start",
                "_type": "a",
                "_attrDef": "p"
            },
            {
                "_key": "pLayoutAlign",
                "_value": "stretch",
                "_type": "a",
                "_attrDef": "p"
            },
            {
                "_key": "[fxShow]",
                "_value": "true",
                "_type": "kv",
                "_attrDef": "p"
            }
        ],
        "2d862419-602a-a275-83ea-87fef31c2b81": {
            "paletteKey": "FlexLayoutRow",
            "parentEditorKey": "c9a75869-c320-bc9d-395d-96ee3f0f336a",
            "commentid": null,
            "designerReference": [
                {
                    "_key": "componentLabel",
                    "_value": "Row",
                    "_type": "kv",
                    "_attrDef": "p",
                    "_useAsLabel": true
                },
                {
                    "_key": "style",
                    "_value": "text-align:center; background-color:rgba(234, 0, 121, 0.8);color:white;",
                    "_type": "kv",
                    "_attrDef": "p"
                },
                {
                    "_key": "class",
                    "_value": "",
                    "_type": "dav",
                    "_attrDef": "p"
                },
                {
                    "_key": "fxFlex",
                    "_value": "",
                    "_type": "kv",
                    "_attrDef": "p"
                },
                {
                    "_key": "fxLayoutGap",
                    "_value": "",
                    "_type": "kv",
                    "_attrDef": "p"
                },
                {
                    "_key": "wrap",
                    "_value": "wrap",
                    "_type": "a",
                    "_attrDef": "p"
                },
                {
                    "_key": "layoutAlign",
                    "_value": "space-between",
                    "_type": "a",
                    "_attrDef": "p"
                },
                {
                    "_key": "pLayoutAlign",
                    "_value": "center",
                    "_type": "a",
                    "_attrDef": "p"
                },
                {
                    "_key": "[fxShow]",
                    "_value": "true",
                    "_type": "kv",
                    "_attrDef": "p"
                }
            ],
            "c6b90b50-4e49-c8ca-b7ba-b3882c176aff": {
                "paletteKey": "Html5",
                "parentEditorKey": "2d862419-602a-a275-83ea-87fef31c2b81",
                "isAdvancedComponent": true,
                "commentid": null,
                "designerReference": [
                    {
                        "_key": "style",
                        "_value": "",
                        "_type": "kv",
                        "_attrDef": "p"
                    },
                    {
                        "_key": "class",
                        "_value": "",
                        "_type": "dav",
                        "_attrDef": "p"
                    },
                    {
                        "_key": "htmlElement",
                        "_value": "div",
                        "_type": "dav",
                        "_attrDef": "p",
                        "_useAsLabel": true
                    },
                    {
                        "_key": "tagType",
                        "_value": "",
                        "_type": "a",
                        "_attrDef": "p",
                        "_visibility": false
                    },
                    {
                        "_key": "name",
                        "_value": "",
                        "_type": "kv",
                        "_attrDef": "p",
                        "_visibility": false
                    },
                    {
                        "_key": "sandbox",
                        "_value": "",
                        "_type": "kv",
                        "_attrDef": "p",
                        "_visibility": false
                    },
                    {
                        "_key": "src",
                        "_value": "",
                        "_type": "kv",
                        "_attrDef": "p",
                        "_visibility": false
                    },
                    {
                        "_key": "srcdoc",
                        "_value": "",
                        "_type": "kv",
                        "_attrDef": "p",
                        "_visibility": false
                    },
                    {
                        "_key": "width",
                        "_value": "",
                        "_type": "kv",
                        "_attrDef": "p",
                        "_visibility": false
                    },
                    {
                        "_key": "[autoplay]",
                        "_value": "",
                        "_type": "kv",
                        "_attrDef": "p",
                        "_visibility": false
                    },
                    {
                        "_key": "[loop]",
                        "_value": "",
                        "_type": "kv",
                        "_attrDef": "p",
                        "_visibility": false
                    },
                    {
                        "_key": "data",
                        "_value": "",
                        "_type": "kv",
                        "_attrDef": "p",
                        "_visibility": false
                    },
                    {
                        "_key": "audioSource",
                        "_value": [],
                        "_type": "a",
                        "_attrDef": "p",
                        "_visibility": false
                    },
                    {
                        "_key": "videoSource",
                        "_value": [],
                        "_type": "a",
                        "_attrDef": "p",
                        "_visibility": false
                    },
                    {
                        "_key": "audioDatasource",
                        "_value": "",
                        "_type": "a",
                        "_attrDef": "p",
                        "_visibility": false
                    },
                    {
                        "_key": "audioSrc",
                        "_value": "",
                        "_type": "a",
                        "_attrDef": "p",
                        "_visibility": false
                    },
                    {
                        "_key": "audioType",
                        "_value": "",
                        "_type": "a",
                        "_attrDef": "p",
                        "_visibility": false
                    },
                    {
                        "_key": "videoDatasource",
                        "_value": "",
                        "_type": "a",
                        "_attrDef": "p",
                        "_visibility": false
                    },
                    {
                        "_key": "videoSrc",
                        "_value": "",
                        "_type": "a",
                        "_attrDef": "p",
                        "_visibility": false
                    },
                    {
                        "_key": "videoType",
                        "_value": "",
                        "_type": "a",
                        "_attrDef": "p",
                        "_visibility": false
                    },
                    {
                        "_key": "(audioplay)",
                        "_value": "",
                        "_type": "a",
                        "_attrDef": "p",
                        "_visibility": false
                    },
                    {
                        "_key": "(videoplay)",
                        "_value": "",
                        "_type": "a",
                        "_attrDef": "p",
                        "_visibility": false
                    },
                    {
                        "_key": "(audiopause)",
                        "_value": "",
                        "_type": "kv",
                        "_attrDef": "p",
                        "_visibility": false
                    },
                    {
                        "_key": "(videopause)",
                        "_value": "",
                        "_type": "kv",
                        "_attrDef": "p",
                        "_visibility": false
                    },
                    {
                        "_key": "(audioended)",
                        "_value": "",
                        "_type": "kv",
                        "_attrDef": "p",
                        "_visibility": false
                    },
                    {
                        "_key": "(videoended)",
                        "_value": "",
                        "_type": "kv",
                        "_attrDef": "p",
                        "_visibility": false
                    }
                ],
                "0b892f72-e62e-a94d-1e5c-bc2ad066cfd5": {
                    "paletteKey": "html-editor",
                    "parentEditorKey": "c6b90b50-4e49-c8ca-b7ba-b3882c176aff",
                    "isAdvancedChildComponent": true,
                    "commentid": null,
                    "designerReference": [
                        {
                            "_key": "style",
                            "_value": "",
                            "_type": "kv",
                            "_attrDef": "p"
                        },
                        {
                            "_key": "class",
                            "_value": "",
                            "_type": "dav",
                            "_attrDef": "p"
                        },
                        {
                            "_key": "html",
                            "_value": "<h1>{{page.user.email}}</h1>",
                            "_type": "a",
                            "_attrDef": "p"
                        }
                    ]
                }
            },
            "038980b0-e267-a684-c92a-198cf096b820": {
                "paletteKey": "NG-RaisedButton",
                "parentEditorKey": "2d862419-602a-a275-83ea-87fef31c2b81",
                "commentid": null,
                "designerReference": [
                    {
                        "_key": "style",
                        "_value": "",
                        "_type": "kv",
                        "_attrDef": "p"
                    },
                    {
                        "_key": "class",
                        "_value": "",
                        "_type": "dav",
                        "_attrDef": "p"
                    },
                    {
                        "_key": "buttonname",
                        "_value": "Sign out",
                        "_type": "a",
                        "_attrDef": "p",
                        "_useAsLabel": true
                    },
                    {
                        "_key": "color",
                        "_value": "",
                        "_type": "kv",
                        "_attrDef": "p"
                    },
                    {
                        "_key": "(click)",
                        "_value": "onSignout()",
                        "_type": "kv",
                        "_attrDef": "p",
                        "objValue": {
                            "nodeID": "sd_nIbNPqPW2aPVnnLR",
                            "functionName": "onSignout",
                            "activeTree": "pages",
                            "z": "sd_eVpn93rzQRgZ6gRI",
                            "input": []
                        }
                    },
                    {
                        "_key": "[disabled]",
                        "_value": "",
                        "_type": "kv",
                        "_attrDef": "p"
                    },
                    {
                        "_key": "[disableRipple]",
                        "_value": "",
                        "_type": "kv",
                        "_attrDef": "p"
                    },
                    {
                        "_key": "type",
                        "_value": "",
                        "_type": "kv",
                        "_attrDef": "p"
                    },
                    {
                        "_key": "routerLink",
                        "_value": "",
                        "_type": "kv",
                        "_attrDef": "p"
                    }
                ]
            }
        },
        "1892907f-03f9-1f2f-840a-06e8c34b9391": {
            "paletteKey": "NG-RaisedButton",
            "parentEditorKey": "c9a75869-c320-bc9d-395d-96ee3f0f336a",
            "commentid": null,
            "designerReference": [
                {
                    "_key": "style",
                    "_value": "width:100px;background-color:rgba(124, 36, 82, 0.8);margin-top:20px;margin-left:50px;",
                    "_type": "kv",
                    "_attrDef": "p"
                },
                {
                    "_key": "class",
                    "_value": "",
                    "_type": "dav",
                    "_attrDef": "p"
                },
                {
                    "_key": "buttonname",
                    "_value": "create event",
                    "_type": "a",
                    "_attrDef": "p",
                    "_useAsLabel": true
                },
                {
                    "_key": "color",
                    "_value": "",
                    "_type": "kv",
                    "_attrDef": "p"
                },
                {
                    "_key": "(click)",
                    "_value": "",
                    "_type": "kv",
                    "_attrDef": "p"
                },
                {
                    "_key": "[disabled]",
                    "_value": "",
                    "_type": "kv",
                    "_attrDef": "p"
                },
                {
                    "_key": "[disableRipple]",
                    "_value": "",
                    "_type": "kv",
                    "_attrDef": "p"
                },
                {
                    "_key": "type",
                    "_value": "",
                    "_type": "kv",
                    "_attrDef": "p"
                },
                {
                    "_key": "routerLink",
                    "_value": "/createevent",
                    "_type": "kv",
                    "_attrDef": "p"
                }
            ]
        },
        "bbb4e35f-44c4-53f0-fa3b-7da336c6e00e": {
            "paletteKey": "FlexLayoutRow",
            "parentEditorKey": "c9a75869-c320-bc9d-395d-96ee3f0f336a",
            "commentid": null,
            "designerReference": [
                {
                    "_key": "componentLabel",
                    "_value": "Row",
                    "_type": "kv",
                    "_attrDef": "p",
                    "_useAsLabel": true
                },
                {
                    "_key": "style",
                    "_value": "",
                    "_type": "kv",
                    "_attrDef": "p"
                },
                {
                    "_key": "class",
                    "_value": "",
                    "_type": "dav",
                    "_attrDef": "p"
                },
                {
                    "_key": "fxFlex",
                    "_value": "",
                    "_type": "kv",
                    "_attrDef": "p"
                },
                {
                    "_key": "fxLayoutGap",
                    "_value": "",
                    "_type": "kv",
                    "_attrDef": "p"
                },
                {
                    "_key": "wrap",
                    "_value": "wrap",
                    "_type": "a",
                    "_attrDef": "p"
                },
                {
                    "_key": "layoutAlign",
                    "_value": "start",
                    "_type": "a",
                    "_attrDef": "p"
                },
                {
                    "_key": "pLayoutAlign",
                    "_value": "stretch",
                    "_type": "a",
                    "_attrDef": "p"
                },
                {
                    "_key": "[fxShow]",
                    "_value": "true",
                    "_type": "kv",
                    "_attrDef": "p"
                }
            ],
            "17a82ea4-76b3-5133-2cba-2c337a78edeb": {
                "paletteKey": "ng-table",
                "parentEditorKey": "bbb4e35f-44c4-53f0-fa3b-7da336c6e00e",
                "isAdvancedComponent": true,
                "commentid": null,
                "designerReference": [
                    {
                        "_key": "componentLabel",
                        "_value": "Table",
                        "_type": "kv",
                        "_attrDef": "p",
                        "_useAsLabel": true
                    },
                    {
                        "_key": "style",
                        "_value": "background:orange:height:100%;width:100%;",
                        "_type": "kv",
                        "_attrDef": "p"
                    },
                    {
                        "_key": "class",
                        "_value": "",
                        "_type": "dav",
                        "_attrDef": "p"
                    },
                    {
                        "_key": "[dataSource]",
                        "_value": "page?.tableData",
                        "_type": "kv",
                        "_attrDef": "p",
                        "value": "page?.tableData"
                    },
                    {
                        "_key": "(rowclick)",
                        "_value": "",
                        "_type": "a",
                        "_attrDef": "p"
                    },
                    {
                        "_key": "header",
                        "_value": true,
                        "_type": "a",
                        "_attrDef": "p",
                        "_visibility": true
                    },
                    {
                        "skipCodegen": true,
                        "_key": "__n_dependant_flows_key__",
                        "_value": [
                            "sd_TSyEr1iokS9g2mT6",
                            "sd_IJtTYf82T73gjbKA",
                            "sd_8KGeLSlkmellpLRZ",
                            "sd_SQjkLkvM6IzOgd3B",
                            "sd_Pl0vATXBJXDTMmZ3"
                        ],
                        "_type": "a",
                        "_attrDef": "c",
                        "_visibility": false
                    }
                ],
                "1593903b-9acc-1a88-eb93-69b21f4e04c1": {
                    "paletteKey": "ng-table-column",
                    "parentEditorKey": "17a82ea4-76b3-5133-2cba-2c337a78edeb",
                    "isAdvancedChildComponent": true,
                    "commentid": null,
                    "designerReference": [
                        {
                            "_key": "Header Label",
                            "_value": "Event Name",
                            "_type": "a",
                            "_attrDef": "p"
                        },
                        {
                            "_key": "matSortHeaderColumn",
                            "_value": "",
                            "_type": "a",
                            "_attrDef": "p"
                        },
                        {
                            "_key": "Mapping",
                            "_value": "{{table.eventName}}",
                            "_type": "ma",
                            "_attrDef": "p",
                            "_useAsLabel": true
                        },
                        {
                            "_key": "columnName",
                            "_value": "",
                            "_type": "dav",
                            "_attrDef": "p",
                            "_visibility": false
                        },
                        {
                            "_key": "headerclass",
                            "_value": "",
                            "_type": "dav",
                            "_attrDef": "p"
                        },
                        {
                            "_key": "columnclass",
                            "_value": "",
                            "_type": "dav",
                            "_attrDef": "p"
                        }
                    ]
                },
                "dba2dca0-23c4-fbe4-0dd0-96569318730f": {
                    "paletteKey": "ng-table-column",
                    "parentEditorKey": "17a82ea4-76b3-5133-2cba-2c337a78edeb",
                    "isAdvancedChildComponent": true,
                    "commentid": null,
                    "designerReference": [
                        {
                            "_key": "Header Label",
                            "_value": "Location",
                            "_type": "a",
                            "_attrDef": "p"
                        },
                        {
                            "_key": "matSortHeaderColumn",
                            "_value": "",
                            "_type": "a",
                            "_attrDef": "p"
                        },
                        {
                            "_key": "Mapping",
                            "_value": "{{table.location}}",
                            "_type": "ma",
                            "_attrDef": "p",
                            "_useAsLabel": true
                        },
                        {
                            "_key": "columnName",
                            "_value": "",
                            "_type": "dav",
                            "_attrDef": "p",
                            "_visibility": false
                        },
                        {
                            "_key": "headerclass",
                            "_value": "",
                            "_type": "dav",
                            "_attrDef": "p"
                        },
                        {
                            "_key": "columnclass",
                            "_value": "",
                            "_type": "dav",
                            "_attrDef": "p"
                        }
                    ]
                },
                "7ad143e1-1874-9252-2ded-ea684b348aca": {
                    "paletteKey": "ng-table-column",
                    "parentEditorKey": "17a82ea4-76b3-5133-2cba-2c337a78edeb",
                    "isAdvancedChildComponent": true,
                    "commentid": null,
                    "designerReference": [
                        {
                            "_key": "Header Label",
                            "_value": "Date",
                            "_type": "a",
                            "_attrDef": "p"
                        },
                        {
                            "_key": "matSortHeaderColumn",
                            "_value": "",
                            "_type": "a",
                            "_attrDef": "p"
                        },
                        {
                            "_key": "Mapping",
                            "_value": "{{table.date|date}}",
                            "_type": "ma",
                            "_attrDef": "p",
                            "_useAsLabel": true
                        },
                        {
                            "_key": "columnName",
                            "_value": "",
                            "_type": "dav",
                            "_attrDef": "p",
                            "_visibility": false
                        },
                        {
                            "_key": "headerclass",
                            "_value": "",
                            "_type": "dav",
                            "_attrDef": "p"
                        },
                        {
                            "_key": "columnclass",
                            "_value": "",
                            "_type": "dav",
                            "_attrDef": "p"
                        }
                    ]
                },
                "d3738183-a791-ca67-7b82-02f8693904a1": {
                    "paletteKey": "ng-table-column",
                    "parentEditorKey": "17a82ea4-76b3-5133-2cba-2c337a78edeb",
                    "isAdvancedChildComponent": true,
                    "commentid": null,
                    "designerReference": [
                        {
                            "_key": "Header Label",
                            "_value": "Description",
                            "_type": "a",
                            "_attrDef": "p"
                        },
                        {
                            "_key": "matSortHeaderColumn",
                            "_value": "",
                            "_type": "a",
                            "_attrDef": "p"
                        },
                        {
                            "_key": "Mapping",
                            "_value": "{{table.description}}",
                            "_type": "ma",
                            "_attrDef": "p",
                            "_useAsLabel": true
                        },
                        {
                            "_key": "columnName",
                            "_value": "",
                            "_type": "dav",
                            "_attrDef": "p",
                            "_visibility": false
                        },
                        {
                            "_key": "headerclass",
                            "_value": "",
                            "_type": "dav",
                            "_attrDef": "p"
                        },
                        {
                            "_key": "columnclass",
                            "_value": "",
                            "_type": "dav",
                            "_attrDef": "p"
                        }
                    ]
                },
                "12598b99-1bc8-1395-7c83-de6dad88fcff": {
                    "paletteKey": "ng-droppable-table-column",
                    "parentEditorKey": "17a82ea4-76b3-5133-2cba-2c337a78edeb",
                    "isAdvancedChildComponent": true,
                    "commentid": null,
                    "designerReference": [
                        {
                            "_key": "Sort Key",
                            "_value": "",
                            "_type": "dav",
                            "_attrDef": "p"
                        },
                        {
                            "_key": "matSortHeaderColumn",
                            "_value": "",
                            "_type": "a",
                            "_attrDef": "p"
                        },
                        {
                            "_key": "columnId",
                            "_value": "30a395e7-cf36-8e9f-4166-1f604879cc09",
                            "_type": "dav",
                            "_attrDef": "p"
                        },
                        {
                            "_key": "Header Label",
                            "_value": "Delete Events",
                            "_type": "a",
                            "_attrDef": "p"
                        },
                        {
                            "_key": "headerclass",
                            "_value": "",
                            "_type": "dav",
                            "_attrDef": "p"
                        },
                        {
                            "_key": "columnclass",
                            "_value": "",
                            "_type": "dav",
                            "_attrDef": "p"
                        }
                    ],
                    "bfa96306-f484-9e58-8473-1c45bdb1c876": {
                        "paletteKey": "NG-icon",
                        "parentEditorKey": "12598b99-1bc8-1395-7c83-de6dad88fcff",
                        "commentid": null,
                        "designerReference": [
                            {
                                "_key": "style",
                                "_value": "",
                                "_type": "kv",
                                "_attrDef": "p"
                            },
                            {
                                "_key": "class",
                                "_value": "",
                                "_type": "dav",
                                "_attrDef": "p"
                            },
                            {
                                "_key": "IconName",
                                "_value": "delete",
                                "_type": "a",
                                "_attrDef": "p",
                                "_useAsLabel": true
                            },
                            {
                                "_key": "[inline]",
                                "_value": "",
                                "_type": "kv",
                                "_attrDef": "p",
                                "_customAttributeFlag": "flowpicker"
                            },
                            {
                                "_key": "color",
                                "_value": "",
                                "_type": "kv",
                                "_attrDef": "p"
                            },
                            {
                                "_key": "(click)",
                                "_value": "deleteEvent(table.eventName)",
                                "_type": "kv",
                                "_attrDef": "c",
                                "_customAttributeFlag": "customInput"
                            }
                        ]
                    }
                },
                "f36481e7-cdce-7893-c801-711b9a790be2": {
                    "paletteKey": "ng-droppable-table-column",
                    "parentEditorKey": "17a82ea4-76b3-5133-2cba-2c337a78edeb",
                    "isAdvancedChildComponent": true,
                    "commentid": null,
                    "designerReference": [
                        {
                            "_key": "Sort Key",
                            "_value": "",
                            "_type": "dav",
                            "_attrDef": "p"
                        },
                        {
                            "_key": "matSortHeaderColumn",
                            "_value": "",
                            "_type": "a",
                            "_attrDef": "p"
                        },
                        {
                            "_key": "columnId",
                            "_value": "4fb49552-c230-5fed-38f6-cd46a74a354a",
                            "_type": "dav",
                            "_attrDef": "p"
                        },
                        {
                            "_key": "Header Label",
                            "_value": "Edit",
                            "_type": "a",
                            "_attrDef": "p"
                        },
                        {
                            "_key": "headerclass",
                            "_value": "",
                            "_type": "dav",
                            "_attrDef": "p"
                        },
                        {
                            "_key": "columnclass",
                            "_value": "",
                            "_type": "dav",
                            "_attrDef": "p"
                        }
                    ],
                    "8e447a17-fcf4-6023-9b04-d1c6e7db3628": {
                        "paletteKey": "NG-icon",
                        "parentEditorKey": "f36481e7-cdce-7893-c801-711b9a790be2",
                        "commentid": null,
                        "designerReference": [
                            {
                                "_key": "style",
                                "_value": "",
                                "_type": "kv",
                                "_attrDef": "p"
                            },
                            {
                                "_key": "class",
                                "_value": "",
                                "_type": "dav",
                                "_attrDef": "p"
                            },
                            {
                                "_key": "IconName",
                                "_value": "edit",
                                "_type": "a",
                                "_attrDef": "p",
                                "_useAsLabel": true
                            },
                            {
                                "_key": "[inline]",
                                "_value": "",
                                "_type": "kv",
                                "_attrDef": "p"
                            },
                            {
                                "_key": "color",
                                "_value": "",
                                "_type": "kv",
                                "_attrDef": "p"
                            },
                            {
                                "_key": "(click)",
                                "_value": "updateEvent(table)",
                                "_type": "kv",
                                "_attrDef": "c",
                                "_customAttributeFlag": "customInput"
                            }
                        ]
                    }
                },
                "b8bc1508-9961-3c49-d657-d34f17ec8e8b": {
                    "paletteKey": "ng-table-paginator",
                    "parentEditorKey": "17a82ea4-76b3-5133-2cba-2c337a78edeb",
                    "isAdvancedComponent": true,
                    "advancedSiblingType": "after",
                    "commentid": null,
                    "designerReference": [
                        {
                            "_key": "style",
                            "_value": "",
                            "_type": "kv",
                            "_attrDef": "p"
                        },
                        {
                            "_key": "class",
                            "_value": "",
                            "_type": "dav",
                            "_attrDef": "p"
                        },
                        {
                            "_key": "[length]",
                            "_value": "",
                            "_type": "kv",
                            "_attrDef": "p"
                        },
                        {
                            "_key": "[pageSize]",
                            "_value": "",
                            "_type": "kv",
                            "_attrDef": "p"
                        },
                        {
                            "_key": "[pageSizeOptions]",
                            "_value": "[5, 10, 25, 100]",
                            "_type": "kv",
                            "_attrDef": "p"
                        },
                        {
                            "_key": "(page)",
                            "_value": "",
                            "_type": "kv",
                            "_attrDef": "p",
                            "value": ""
                        },
                        {
                            "skipCodegen": true,
                            "_key": "__n_dependant_flows_key__",
                            "_value": [
                                "sd_NfyjUYwCC3vaELlS",
                                "sd_tLXnh7O8SW8IP8XK"
                            ],
                            "_type": "a",
                            "_attrDef": "p",
                            "_visibility": false
                        }
                    ]
                },
                "28b00d4c-c2be-61f1-1b3d-2177092aee9b": {
                    "paletteKey": "ng-table-column",
                    "parentEditorKey": "17a82ea4-76b3-5133-2cba-2c337a78edeb",
                    "isAdvancedChildComponent": true,
                    "commentid": null,
                    "designerReference": [
                        {
                            "_key": "Header Label",
                            "_value": "Booked Number",
                            "_type": "a",
                            "_attrDef": "p"
                        },
                        {
                            "_key": "matSortHeaderColumn",
                            "_value": "",
                            "_type": "a",
                            "_attrDef": "p"
                        },
                        {
                            "_key": "Mapping",
                            "_value": "{{table.bookeBy.length}}",
                            "_type": "ma",
                            "_attrDef": "p",
                            "_useAsLabel": true
                        },
                        {
                            "_key": "columnName",
                            "_value": "",
                            "_type": "dav",
                            "_attrDef": "p",
                            "_visibility": false
                        },
                        {
                            "_key": "headerclass",
                            "_value": "",
                            "_type": "dav",
                            "_attrDef": "p"
                        },
                        {
                            "_key": "columnclass",
                            "_value": "",
                            "_type": "dav",
                            "_attrDef": "p"
                        }
                    ]
                },
                "b6185ecf-0e5a-8cda-a416-9738c89eddb6": {
                    "paletteKey": "ng-droppable-table-column",
                    "parentEditorKey": "17a82ea4-76b3-5133-2cba-2c337a78edeb",
                    "isAdvancedChildComponent": true,
                    "commentid": null,
                    "designerReference": [
                        {
                            "_key": "Sort Key",
                            "_value": "",
                            "_type": "dav",
                            "_attrDef": "p"
                        },
                        {
                            "_key": "matSortHeaderColumn",
                            "_value": "",
                            "_type": "a",
                            "_attrDef": "p"
                        },
                        {
                            "_key": "columnId",
                            "_value": "8efadbca-6923-c7d3-98c6-54a64a48d8e7",
                            "_type": "dav",
                            "_attrDef": "p"
                        },
                        {
                            "_key": "Header Label",
                            "_value": "",
                            "_type": "a",
                            "_attrDef": "p"
                        },
                        {
                            "_key": "headerclass",
                            "_value": "",
                            "_type": "dav",
                            "_attrDef": "p"
                        },
                        {
                            "_key": "columnclass",
                            "_value": "",
                            "_type": "dav",
                            "_attrDef": "p"
                        }
                    ],
                    "efda8ce5-2f7d-7ce4-8a8f-7d54b467a627": {
                        "paletteKey": "NG-RaisedButton",
                        "parentEditorKey": "b6185ecf-0e5a-8cda-a416-9738c89eddb6",
                        "commentid": null,
                        "designerReference": [
                            {
                                "_key": "style",
                                "_value": "color:rgba(129, 31, 81, 0.8);border:1px solid red;",
                                "_type": "kv",
                                "_attrDef": "p"
                            },
                            {
                                "_key": "class",
                                "_value": "",
                                "_type": "dav",
                                "_attrDef": "p"
                            },
                            {
                                "_key": "buttonname",
                                "_value": "view booked users",
                                "_type": "a",
                                "_attrDef": "p",
                                "_useAsLabel": true
                            },
                            {
                                "_key": "color",
                                "_value": "",
                                "_type": "kv",
                                "_attrDef": "p"
                            },
                            {
                                "_key": "(click)",
                                "_value": "showBookedUser(table.bookeBy)",
                                "_type": "kv",
                                "_attrDef": "p",
                                "_customAttributeFlag": "customInput"
                            },
                            {
                                "_key": "[disabled]",
                                "_value": "",
                                "_type": "kv",
                                "_attrDef": "p"
                            },
                            {
                                "_key": "[disableRipple]",
                                "_value": "",
                                "_type": "kv",
                                "_attrDef": "p"
                            },
                            {
                                "_key": "type",
                                "_value": "",
                                "_type": "kv",
                                "_attrDef": "p"
                            },
                            {
                                "_key": "routerLink",
                                "_value": "",
                                "_type": "kv",
                                "_attrDef": "p"
                            }
                        ]
                    }
                },
                "e89c7317-4199-d9de-7279-f862cd9066ee": {
                    "paletteKey": "ng-table-filter",
                    "parentEditorKey": "17a82ea4-76b3-5133-2cba-2c337a78edeb",
                    "isAdvancedComponent": true,
                    "advancedSiblingType": "before",
                    "commentid": null,
                    "designerReference": [
                        {
                            "_key": "style",
                            "_value": "",
                            "_type": "kv",
                            "_attrDef": "p"
                        },
                        {
                            "_key": "class",
                            "_value": "",
                            "_type": "dav",
                            "_attrDef": "p"
                        },
                        {
                            "_key": "(tableFilterFunction)",
                            "_value": "onFilter_3($event)",
                            "_type": "dav",
                            "_attrDef": "p",
                            "value": "onFilter_3($event)",
                            "_customAttributeFlag": "flowpicker",
                            "objValue": {
                                "activeTree": "pages",
                                "functionName": "onFilter_3",
                                "input": [
                                    "$event"
                                ],
                                "nodeID": "sd_7LBNVW1pWG3cwatl",
                                "z": ""
                            }
                        },
                        {
                            "_key": "placeholder",
                            "_value": "Search",
                            "_type": "kv",
                            "_attrDef": "p"
                        },
                        {
                            "_key": "layoutAlign",
                            "_value": "end",
                            "_type": "a",
                            "_attrDef": "p"
                        },
                        {
                            "_key": "fxFlex",
                            "_value": "end",
                            "_type": "a",
                            "_attrDef": "p"
                        },
                        {
                            "skipCodegen": true,
                            "_key": "__n_dependant_flows_key__",
                            "_value": [
                                "sd_mDQUgUTVSnkA3mnd",
                                "sd_7LBNVW1pWG3cwatl"
                            ],
                            "_type": "a",
                            "_attrDef": "p",
                            "_visibility": false
                        }
                    ]
                }
            }
        },
        "a76ae20b-d651-164a-d7ef-385eb17a71b5": {
            "paletteKey": "FlexLayoutRow",
            "parentEditorKey": "c9a75869-c320-bc9d-395d-96ee3f0f336a",
            "commentid": null,
            "designerReference": [
                {
                    "_key": "componentLabel",
                    "_value": "Row",
                    "_type": "kv",
                    "_attrDef": "p",
                    "_useAsLabel": true
                },
                {
                    "_key": "style",
                    "_value": "",
                    "_type": "kv",
                    "_attrDef": "p"
                },
                {
                    "_key": "class",
                    "_value": "",
                    "_type": "dav",
                    "_attrDef": "p"
                },
                {
                    "_key": "fxFlex",
                    "_value": "",
                    "_type": "kv",
                    "_attrDef": "p"
                },
                {
                    "_key": "fxLayoutGap",
                    "_value": "",
                    "_type": "kv",
                    "_attrDef": "p"
                },
                {
                    "_key": "wrap",
                    "_value": "wrap",
                    "_type": "a",
                    "_attrDef": "p"
                },
                {
                    "_key": "layoutAlign",
                    "_value": "center",
                    "_type": "a",
                    "_attrDef": "p"
                },
                {
                    "_key": "pLayoutAlign",
                    "_value": "center",
                    "_type": "a",
                    "_attrDef": "p"
                },
                {
                    "_key": "[fxShow]",
                    "_value": "true",
                    "_type": "kv",
                    "_attrDef": "p"
                },
                {
                    "_key": "*ngIf",
                    "_value": "!page.myEvents.length",
                    "_type": "kv",
                    "_attrDef": "c"
                }
            ],
            "3f71d3b9-3946-f247-ccb1-d68c89ea60cd": {
                "paletteKey": "Html5",
                "parentEditorKey": "a76ae20b-d651-164a-d7ef-385eb17a71b5",
                "isAdvancedComponent": true,
                "commentid": null,
                "designerReference": [
                    {
                        "_key": "style",
                        "_value": "",
                        "_type": "kv",
                        "_attrDef": "p"
                    },
                    {
                        "_key": "class",
                        "_value": "",
                        "_type": "dav",
                        "_attrDef": "p"
                    },
                    {
                        "_key": "htmlElement",
                        "_value": "div",
                        "_type": "dav",
                        "_attrDef": "p",
                        "_useAsLabel": true
                    },
                    {
                        "_key": "tagType",
                        "_value": "",
                        "_type": "a",
                        "_attrDef": "p",
                        "_visibility": false
                    },
                    {
                        "_key": "name",
                        "_value": "",
                        "_type": "kv",
                        "_attrDef": "p",
                        "_visibility": false
                    },
                    {
                        "_key": "sandbox",
                        "_value": "",
                        "_type": "kv",
                        "_attrDef": "p",
                        "_visibility": false
                    },
                    {
                        "_key": "src",
                        "_value": "",
                        "_type": "kv",
                        "_attrDef": "p",
                        "_visibility": false
                    },
                    {
                        "_key": "srcdoc",
                        "_value": "",
                        "_type": "kv",
                        "_attrDef": "p",
                        "_visibility": false
                    },
                    {
                        "_key": "width",
                        "_value": "",
                        "_type": "kv",
                        "_attrDef": "p",
                        "_visibility": false
                    },
                    {
                        "_key": "[autoplay]",
                        "_value": "",
                        "_type": "kv",
                        "_attrDef": "p",
                        "_visibility": false
                    },
                    {
                        "_key": "[loop]",
                        "_value": "",
                        "_type": "kv",
                        "_attrDef": "p",
                        "_visibility": false
                    },
                    {
                        "_key": "data",
                        "_value": "",
                        "_type": "kv",
                        "_attrDef": "p",
                        "_visibility": false
                    },
                    {
                        "_key": "audioSource",
                        "_value": [],
                        "_type": "a",
                        "_attrDef": "p",
                        "_visibility": false
                    },
                    {
                        "_key": "videoSource",
                        "_value": [],
                        "_type": "a",
                        "_attrDef": "p",
                        "_visibility": false
                    },
                    {
                        "_key": "audioDatasource",
                        "_value": "",
                        "_type": "a",
                        "_attrDef": "p",
                        "_visibility": false
                    },
                    {
                        "_key": "audioSrc",
                        "_value": "",
                        "_type": "a",
                        "_attrDef": "p",
                        "_visibility": false
                    },
                    {
                        "_key": "audioType",
                        "_value": "",
                        "_type": "a",
                        "_attrDef": "p",
                        "_visibility": false
                    },
                    {
                        "_key": "videoDatasource",
                        "_value": "",
                        "_type": "a",
                        "_attrDef": "p",
                        "_visibility": false
                    },
                    {
                        "_key": "videoSrc",
                        "_value": "",
                        "_type": "a",
                        "_attrDef": "p",
                        "_visibility": false
                    },
                    {
                        "_key": "videoType",
                        "_value": "",
                        "_type": "a",
                        "_attrDef": "p",
                        "_visibility": false
                    },
                    {
                        "_key": "(audioplay)",
                        "_value": "",
                        "_type": "a",
                        "_attrDef": "p",
                        "_visibility": false
                    },
                    {
                        "_key": "(videoplay)",
                        "_value": "",
                        "_type": "a",
                        "_attrDef": "p",
                        "_visibility": false
                    },
                    {
                        "_key": "(audiopause)",
                        "_value": "",
                        "_type": "kv",
                        "_attrDef": "p",
                        "_visibility": false
                    },
                    {
                        "_key": "(videopause)",
                        "_value": "",
                        "_type": "kv",
                        "_attrDef": "p",
                        "_visibility": false
                    },
                    {
                        "_key": "(audioended)",
                        "_value": "",
                        "_type": "kv",
                        "_attrDef": "p",
                        "_visibility": false
                    },
                    {
                        "_key": "(videoended)",
                        "_value": "",
                        "_type": "kv",
                        "_attrDef": "p",
                        "_visibility": false
                    }
                ],
                "e26b6e8a-7d00-c5d6-693a-9ddbe0d11eeb": {
                    "paletteKey": "html-editor",
                    "parentEditorKey": "3f71d3b9-3946-f247-ccb1-d68c89ea60cd",
                    "isAdvancedChildComponent": true,
                    "commentid": null,
                    "designerReference": [
                        {
                            "_key": "style",
                            "_value": "",
                            "_type": "kv",
                            "_attrDef": "p"
                        },
                        {
                            "_key": "class",
                            "_value": "",
                            "_type": "dav",
                            "_attrDef": "p"
                        },
                        {
                            "_key": "html",
                            "_value": "<h1>No Events</h1>",
                            "_type": "a",
                            "_attrDef": "p"
                        }
                    ]
                }
            }
        }
    }
}
